Metadata-Version: 1.2
Name: ASEkit
Version: 1.1
Summary: ASEkit: A kit apply for ASE analysis pipeline
Home-page: UNKNOWN
Author: huangke
Author-email: huangke@shanghaitech.edu.cn
Maintainer: huangke
Maintainer-email: huangke@shanghaitech.edu.cn
License: BSD (3-clause)
Platform: UNKNOWN
Classifier: Intended Audience :: Science/Research
Classifier: Programming Language :: Python :: 3.5
Classifier: License :: OSI Approved :: BSD License
Classifier: Topic :: Scientific/Engineering :: Bio-Informatics
Classifier: Operating System :: POSIX
Classifier: Operating System :: POSIX :: Linux
Classifier: Operating System :: MacOS
